dbutil
