Metadata-Version: 1.0
Name: dbutil
Version: 0.5.0
Summary: Minimalist utility functions for the Python DB API
Home-page: http://github.com/thomaslee/python-dbutil
Author: Tom Lee
Author-email: pypi@tomlee.co
License: MIT
Platform: UNKNOWN
